{
  "imports": {
    "@polkadot/api": "npm:@polkadot/api@9.14.2",
    "@polkadot/api-contract": "npm:@polkadot/api-contract@9.14.2",
    "@polkadot/api-contract/base/contract": "npm:@polkadot/api-contract@9.14.2/base/Contract",
    "@polkadot/api-contract/types": "npm:@polkadot/api-contract@9.14.2/types",
    "@polkadot/api-derive": "npm:@polkadot/api-derive@9.14.2",
    "@polkadot/api-derive/types": "npm:@polkadot/api-derive@9.14.2/types",
    "@polkadot/api/types": "npm:@polkadot/api@9.14.2/types",
    "@polkadot/extension-dapp": "npm:@polkadot/extension-dapp@0.44.8",
    "@polkadot/extension-inject": "npm:@polkadot/extension-inject@0.44.8",
    "@polkadot/extension-inject/types": "npm:@polkadot/extension-inject@0.44.8/types",
    "@polkadot/rpc-provider": "npm:@polkadot/rpc-provider@9.14.2",
    "@polkadot/rpc-provider/types": "npm:@polkadot/rpc-provider@9.14.2/types",
    "@polkadot/types": "npm:@polkadot/types@9.14.2",
    "@polkadot/types-codec/types": "npm:@polkadot/types-codec@9.14.2/types",
    "@polkadot/types/interfaces": "npm:@polkadot/types@9.14.2/interfaces",
    "@polkadot/types/types": "npm:@polkadot/types@9.14.2/types",
    "@polkadot/util": "npm:@polkadot/util@10.4.1",
    "@talisman/connect-wallets": "npm:@talismn/connect-wallets@1.2.3",
    "bn.js": "npm:bn.js@5.2.1",
    "react": "https://cdn.skypack.dev/react?dts",
    "react/jsx-runtime": "https://cdn.skypack.dev/react/jsx-runtime?dts",
    "react/jsx-dev-runtime": "https://cdn.skypack.dev/react/jsx-dev-runtime?dts"
  }
}
